{"BioData":"Republican, of Castlewood, SD; born in Watertown, SD, November 30, 1971; professional: farmer; rancher; member of South Dakota State House of Representatives, 2007-10; committees: Ways & Means; elected to the 112th Congress on November 2, 2010; reelected to each succeeding Congress.","BirthDate":"11\/30\/1971","BirthPlace":"Watertown, SD","CongressionalDescription":"114th Congress","Counties":"","District":"At Large","ElectedDate":"3\/14\/2016","Email":"","FirstName":"Kristi","FourYearTerm":false,"Hometown":"Castlewood","ImageToolTip":"","ImageUrl":"http:\/\/www.memberguide.gpo.gov\/PictorialImages\/114_rp_sd_0_noem_kristi.jpg","LastName":"Noem","MemIndexId":"N000184","MemberId":9872,"MemberType":"Representative","MemberTypeId":"RP","MiddleName":"","Name":"Kristi  Noem ","OfficeList":[{"City":"Aberdeen","Fax":"","MemberId":9872,"MemberOfficeId":55228,"OfficeBuilding":"","OfficeDescription":"District","Phone":"6052622862","StaffList":null,"StateDescription":"South Dakota","Street":"415 South Main Street, Suite 203","TDD":"","TTY":"","Zip":"57401"},{"City":"Watertown","Fax":"","MemberId":9872,"MemberOfficeId":55229,"OfficeBuilding":"","OfficeDescription":"District","Phone":"6058782868","StaffList":[{"FirstName":"Beth","LastName":"Hollatz","MemberOfficeId":55229,"MemberOfficeStaffId":72109,"MiddleName":"","OfficeStaffTypeDescription":"State Director","OfficeStaffTypeId":"R"}],"StateDescription":"South Dakota","Street":"818 S. Broadway Suite 113","TDD":"","TTY":"","Zip":"57201"},{"City":"Rapid City","Fax":"","MemberId":9872,"MemberOfficeId":55227,"OfficeBuilding":"","OfficeDescription":"District","Phone":"6057914673","StaffList":[{"FirstName":"Brad","LastName":"Otten","MemberOfficeId":55227,"MemberOfficeStaffId":72108,"MiddleName":"","OfficeStaffTypeDescription":"West River Director","OfficeStaffTypeId":"LN"}],"StateDescription":"South Dakota","Street":"343 Quincy Street","TDD":"","TTY":"","Zip":"57701"},{"City":"Washington","Fax":"2022255823","MemberId":9872,"MemberOfficeId":55225,"OfficeBuilding":"2422 Rayburn House Office Building","OfficeDescription":"Washington","Phone":"2022252801","StaffList":[{"FirstName":"Jordan","LastName":"Stoick","MemberOfficeId":55225,"MemberOfficeStaffId":72103,"MiddleName":"","OfficeStaffTypeDescription":"Chief Of Staff","OfficeStaffTypeId":"A"},{"FirstName":"Andrew","LastName":"Christianson","MemberOfficeId":55225,"MemberOfficeStaffId":72104,"MiddleName":"","OfficeStaffTypeDescription":"Legislative Director","OfficeStaffTypeId":"I"},{"FirstName":"Brittany","LastName":"Comins","MemberOfficeId":55225,"MemberOfficeStaffId":72105,"MiddleName":"","OfficeStaffTypeDescription":"Communications Director","OfficeStaffTypeId":"H"},{"FirstName":"Christiana","LastName":"Frazee","MemberOfficeId":55225,"MemberOfficeStaffId":72106,"MiddleName":"","OfficeStaffTypeDescription":"Scheduler","OfficeStaffTypeId":"D"}],"StateDescription":"District of Columbia","Street":"","TDD":"","TTY":"","Zip":"20515"},{"City":"Sioux Falls","Fax":"","MemberId":9872,"MemberOfficeId":55226,"OfficeBuilding":"","OfficeDescription":"District","Phone":"6052752868","StaffList":[{"FirstName":"Andrew","LastName":"Curley","MemberOfficeId":55226,"MemberOfficeStaffId":72107,"MiddleName":"","OfficeStaffTypeDescription":"Southeast Director","OfficeStaffTypeId":"KY"}],"StateDescription":"South Dakota","Street":"300 N. Dakota Avenue, Suite 314","TDD":"","TTY":"","Zip":"57104"}],"PartyDescription":"Republican","PartyId":"R","Prefix":"","PriorSenateService":false,"PublicUrl":"http:\/\/memberguide.gpo.gov\/114\/RP\/Noem","SocialMediaList":null,"StateDescription":"South Dakota","StateId":"SD","Suffix":null,"TermCount":3,"TermsConsecutive":true,"ThumbNailImageUrl":"http:\/\/www.memberguide.gpo.gov\/ReadLibraryItem.ashx?SFN=Axp2GIJcTfKXoSKnVSZxrBpM2ks3JoZkJ1gH61Uk0KQ=&I=1MKI2SYWd4A=&W=H5kgshlSd9Y=&H=H5kgshlSd9Y=","Title":"","Url":"http:\/\/www.noem.house.gov","ZipCodes":"57001-07, 57010, 57012-18, 57020-22, 57024-59, 57061-73, 57075-79, 57101, 57103-10, 57117-18, 57186, 57188-89, 57192-98, 57201, 57212-14, 57216-21, 57223-27, 57231-39, 57241-43, 57245-49, 57251-53, 57255-66, 57268-74, 57276, 57278-79, 57301, 57311-15, 57317, 57319, 57321-26, 57328-32, 57334-35, 57337, 57339-42, 57344-46, 57348-50, 57353-56, 57358-59, 57361-71, 57373-76, 57379-86, 57399, 57401-02, 57420-22, 57424, 57426-30, 57432-42, 57445-46, 57448-52, 57454-57, 57460-61, 57465-77, 57479, 57481, 57501, 57520-23, 57528-29, 57531-34, 57536-38, 57540-44, 57547-48, 57551-53, 57555, 57559-60, 57562-64, 57566-72, 57574, 57576-77, 57579-80, 57584-85, 57601, 57620-23, 57625-26, 57630-34, 57636, 57638-42, 57644-46, 57648-52, 57656-61, 57701-03, 57706, 57709, 57714, 57716-20, 57722, 57724-25, 57730, 57732, 57735, 57737-38, 57741, 57744-45, 57747-48, 57750-52, 57754-56, 57758-64, 57766-67, 57769-70, 57772-73, 57775-77, 57779-80, 57782-83, 57785, 57787-88, 57790-94, 57799"}