{"BioData":"Democrat, of Bloomfield Township, MI; born in Pontiac, MI, December 1, 1958; education: B.A., Alma College, Alma, MI, 1980; M.B.A. in Finance, University of Detroit, Detroit, MI, 1984; J.D., Wayne State University Law School, Detroit, MI, 1989; M.A. in Philosophy, Michigan State University, East Lansing, MI, 2007; professional: Assistant Vice President, Merrill Lynch, 1980-89; Vice President, UBS\/Paine Webber, 1989-2003; former arbitrator, Financial Industry Regulatory Authority; At-Large City Councilman, Rochester Hills, MI, 1991-93; Lieutenant Commander, Seabee Combat Warfare Specialist, U.S. Navy Reserve, 1993-2000, 2001-05; Michigan State Senator, 1995-2002; Chief Administrative Officer for the Bureau of Investments, State of Michigan, 2003; Lottery Commissioner, State of Michigan, 2003-07; former instructor, Oakland University and Wayne State University; Griffin Endowed Chair in American Government, Central Michigan University, 2007-08; member, Michigan Bar Association; religion: Episcopalian; married: Colleen Ochoa Peters; three children: Gary Jr., Madeleine, and Alana; committees: Commerce, Science, and Transportation; Homeland Security and Governmental Affairs; Small Business and Entrepreneurship; Joint Economic Committee; elected to the U.S. House of Representatives in 2008, 2010 and 2012; elected to the U.S. Senate on November 4, 2014.","BirthDate":"12\/1\/1958","BirthPlace":"Pontiac, MI","CongressionalDescription":"114th Congress","Counties":"","District":"","ElectedDate":"1\/6\/2015","Email":"","FirstName":"Gary","FourYearTerm":false,"Hometown":"Bloomfield Hills","ImageToolTip":"","ImageUrl":"http:\/\/www.memberguide.gpo.gov\/PictorialImages\/114_SR_MI_Peters_Gary.jpg","LastName":"Peters","MemIndexId":"P000595","MemberId":10078,"MemberType":"Senator","MemberTypeId":"SR","MiddleName":"C.","Name":"Gary  C. Peters ","OfficeList":[{"City":"Detroit","Fax":"","MemberId":10078,"MemberOfficeId":54529,"OfficeBuilding":"","OfficeDescription":"District","Phone":"3132266020","StaffList":[{"FirstName":"Elise","LastName":"Lancaster","MemberOfficeId":54529,"MemberOfficeStaffId":71210,"MiddleName":"","OfficeStaffTypeDescription":"State Director","OfficeStaffTypeId":"R"}],"StateDescription":"Michigan","Street":"477 Michigan Avenue, Suite 1860","TDD":"","TTY":"","Zip":"48226"},{"City":"Washington","Fax":"2022247387","MemberId":10078,"MemberOfficeId":54528,"OfficeBuilding":"724 Hart Senate Office Building","OfficeDescription":"Washington","Phone":"2022246221","StaffList":[{"FirstName":"Eric","LastName":"Feldman","MemberOfficeId":54528,"MemberOfficeStaffId":71207,"MiddleName":"","OfficeStaffTypeDescription":"Chief Of Staff","OfficeStaffTypeId":"A"},{"FirstName":"David","LastName":"Weinberg","MemberOfficeId":54528,"MemberOfficeStaffId":71208,"MiddleName":"","OfficeStaffTypeDescription":"Legislative Director","OfficeStaffTypeId":"I"},{"FirstName":"Amber","LastName":"Moon","MemberOfficeId":54528,"MemberOfficeStaffId":71209,"MiddleName":"","OfficeStaffTypeDescription":"Communications Director","OfficeStaffTypeId":"H"}],"StateDescription":"District of Columbia","Street":"","TDD":"","TTY":"","Zip":"20510"}],"PartyDescription":"Democrat","PartyId":"D","Prefix":"","PriorSenateService":false,"PublicUrl":"http:\/\/memberguide.gpo.gov\/114\/SR\/Peters","SocialMediaList":[{"MembersSocialMediaID":690,"MemberId":10078,"SocialMediaID":1,"Url":"https:\/\/www.facebook.com\/sengarypeters","Comments":"","MemberName":"Peters, Gary  C.","SocialMediaDescription":"Face book Url","SocialMediaTypeName":"Facebook"},{"MembersSocialMediaID":691,"MemberId":10078,"SocialMediaID":2,"Url":"http:\/\/www.twitter.com\/sengarypeters","Comments":"","MemberName":"Peters, Gary  C.","SocialMediaDescription":"Twitter","SocialMediaTypeName":"Twitter"},{"MembersSocialMediaID":692,"MemberId":10078,"SocialMediaID":7,"Url":"http:\/\/www.instagram.com\/sengarypeters","Comments":"","MemberName":"Peters, Gary  C.","SocialMediaDescription":"Instagram","SocialMediaTypeName":"Instagram"}],"StateDescription":"Michigan","StateId":"MI","Suffix":null,"TermCount":0,"TermsConsecutive":true,"ThumbNailImageUrl":"http:\/\/www.memberguide.gpo.gov\/ReadLibraryItem.ashx?SFN=qB3gDupgxehB9qkqKjuNKLNaxTkkzxHGryIPitP7YLs=&I=1MKI2SYWd4A=&W=H5kgshlSd9Y=&H=H5kgshlSd9Y=","Title":"","Url":"http:\/\/www.peters.senate.gov","ZipCodes":""}