{"BioData":"Republican, of Salem, MO; born in St. Louis, MO, June 16, 1980; education: graduate of Salem High School, received B.S. degrees, agricultural economics and business administration with an emphasis in finance, University of Missouri, Columbia; earned law degree from Oklahoma City University School of Law; Trinity College, Cambridge, England; professional: attorney; real estate agent; small business owner and fourth generation owner of the family farm; religion: Assemblies of God; NRA; Missouri Farm Bureau; former president, current member of the Salem FFA Alumni Association; holds an American FFA degree; elected to the Missouri State House of Representatives, 2005 (special election), 2006, 2008; leadership: served as Majority Whip in 96th General Assembly; youngest Speaker Pro Tem in 97th General Assembly; committees: Ways and Means; elected by special election on June 4, 2013 to the 113th Congress, to fill the vacancy caused by the resignation of United States Representative Jo Ann Emerson; reelected to the 114th Congress on November 4, 2014.","BirthDate":"6\/16\/1980","BirthPlace":"St. Louis, MO","CongressionalDescription":"114th Congress","Counties":"Bollinger, Butler, Cape Girardeau, Carter, Crawford, Dent, Douglas, Dunklin, Howell, Iron, Jefferson (part), Madison, Mississippi, New Madrid, Oregon, Ozark, Pemiscot, Perry, Phelps, Reynolds, Ripley, Scott, Shannon, St. Francois, Ste. Genevieve, Stoddard, Texas, Washington, Wayne and Wright. Population (2010), 748,616.","District":"8","ElectedDate":"3\/14\/2016","Email":"","FirstName":"Jason","FourYearTerm":false,"Hometown":"Salem","ImageToolTip":"","ImageUrl":"http:\/\/www.memberguide.gpo.gov\/PictorialImages\/114_RP_MO_8_Smith_Jason.jpg","LastName":"Smith","MemIndexId":"S001195","MemberId":9747,"MemberType":"Representative","MemberTypeId":"RP","MiddleName":"T.","Name":"Jason  T. Smith ","OfficeList":[{"City":"Farmington","Fax":"","MemberId":9747,"MemberOfficeId":54666,"OfficeBuilding":"","OfficeDescription":"District","Phone":"5737569755","StaffList":null,"StateDescription":"Missouri","Street":"22 East Columbia","TDD":"","TTY":"","Zip":"63640"},{"City":"West Plains","Fax":"","MemberId":9747,"MemberOfficeId":54667,"OfficeBuilding":"","OfficeDescription":"District","Phone":"4172551515","StaffList":null,"StateDescription":"Missouri","Street":"35 Court Square, Suite 300","TDD":"","TTY":"","Zip":"65775"},{"City":"Poplar Bluff","Fax":"","MemberId":9747,"MemberOfficeId":54668,"OfficeBuilding":"","OfficeDescription":"District","Phone":"","StaffList":null,"StateDescription":"Missouri","Street":"2911 North Westwood Boulevard, Suite C","TDD":"","TTY":"","Zip":"63907"},{"City":"Washington","Fax":"2022260326","MemberId":9747,"MemberOfficeId":54663,"OfficeBuilding":"1118 Longworth House Office Building","OfficeDescription":"Washington","Phone":"2022254404","StaffList":[{"FirstName":"Josh","LastName":"Haynes","MemberOfficeId":54663,"MemberOfficeStaffId":71395,"MiddleName":"","OfficeStaffTypeDescription":"Chief Of Staff","OfficeStaffTypeId":"A"},{"FirstName":"Estephania","LastName":"Gongora","MemberOfficeId":54663,"MemberOfficeStaffId":71396,"MiddleName":"","OfficeStaffTypeDescription":"Executive Assistant\/Scheduler","OfficeStaffTypeId":"HZ"}],"StateDescription":"District of Columbia","Street":"","TDD":"","TTY":"","Zip":"20515"},{"City":"Cape Girardeau","Fax":"","MemberId":9747,"MemberOfficeId":54664,"OfficeBuilding":"","OfficeDescription":"District","Phone":"5733350101","StaffList":null,"StateDescription":"Missouri","Street":"2502 Tanner Drive, Suite 205","TDD":"","TTY":"","Zip":"63703"},{"City":"Rolla","Fax":"","MemberId":9747,"MemberOfficeId":54665,"OfficeBuilding":"","OfficeDescription":"District","Phone":"5733642455","StaffList":null,"StateDescription":"Missouri","Street":"830A South Bishop","TDD":"","TTY":"","Zip":"65401"}],"PartyDescription":"Republican","PartyId":"R","Prefix":"","PriorSenateService":false,"PublicUrl":"http:\/\/memberguide.gpo.gov\/114\/RP\/Smith","SocialMediaList":[{"MembersSocialMediaID":710,"MemberId":9747,"SocialMediaID":1,"Url":"http:\/\/www.facebook.com\/repjasonsmith","Comments":"","MemberName":"Smith, Jason  T.","SocialMediaDescription":"Face book Url","SocialMediaTypeName":"Facebook"},{"MembersSocialMediaID":711,"MemberId":9747,"SocialMediaID":2,"Url":"http:\/\/twitter.com\/repjasonsmith","Comments":"","MemberName":"Smith, Jason  T.","SocialMediaDescription":"Twitter","SocialMediaTypeName":"Twitter"}],"StateDescription":"Missouri","StateId":"MO","Suffix":null,"TermCount":2,"TermsConsecutive":true,"ThumbNailImageUrl":"http:\/\/www.memberguide.gpo.gov\/ReadLibraryItem.ashx?SFN=5nCjb1OTNdebGkoHVlwi8A0ViC45AvSVSawKZQB3pPc=&I=1MKI2SYWd4A=&W=H5kgshlSd9Y=&H=H5kgshlSd9Y=","Title":"","Url":"http:\/\/jasonsmith.house.gov","ZipCodes":"63036, 63071, 63601, 63620-26, 63628-33, 63636-38, 63640, 63648, 63650-51, 63653-56, 63660, 63662-66, 63674-75, 63701-03, 63730, 63732, 63735-40, 63742-48, 63750-52, 63755, 63758, 63760, 63763-64, 63766-67, 63769-72, 63774-76, 63779-85, 63787, 63801, 63820-30, 63833-34, 63837, 63839-41, 63845-53, 63855, 63857, 63860, 63862-63, 63866-70, 63873-82, 63901-02, 63931-45, 63950-57, 63960-67, 65401-02, 65409, 65436, 65438-41, 65444, 65446, 65449, 65453, 65456, 65459, 65461-62, 65464, 65466, 65468, 65479, 65483-84, 65501, 65529, 65532, 65541-42, 65546, 65548, 65550, 65552, 65555, 65557, 65564-66, 65570-71, 65586, 65588-89, 65606, 65608-09, 65614, 65616, 65618, 65620, 65626-27, 65629, 65637-38, 65652-53, 65655, 65660, 65662, 65666-67, 65676, 65679-80, 65688-90, 65692, 65701-02, 65704, 65711, 65713, 65715, 65717, 65720, 65729, 65731, 65733, 65740-41, 65744, 65746, 65753, 65755, 65759-62, 65766, 65768, 65773, 65775, 65777-78, 65784, 65788-91, 65793"}